mampoer/__init__.py
mampoer/cli.py
mampoer/mampoer.py
mampoer/templates/mampoer_generic/README
mampoer/templates/mampoer_generic/env.py
mampoer/templates/mampoer_generic/mampoer.ini.mako
mampoer/templates/mampoer_generic/script.py.mako
mampoer-0.1.4.dist-info/AUTHORS.rst
mampoer-0.1.4.dist-info/LICENSE
mampoer-0.1.4.dist-info/METADATA
mampoer-0.1.4.dist-info/WHEEL
mampoer-0.1.4.dist-info/entry_points.txt
mampoer-0.1.4.dist-info/top_level.txt
mampoer-0.1.4.dist-info/RECORD
