Metadata-Version: 2.1
Name: mampoer
Version: 0.1.4
Summary: Dynamic implementation of Alembic and SQLAlchemy
Home-page: https://github.com/zodimo/mampoer
Author: Jaco Labuschagne
Author-email: zodimo@gmail.com
License: MIT license
Keywords: mampoer
Platform: UNKNOWN
Classifier: Development Status :: 2 - Pre-Alpha
Classifier: Intended Audience :: Developers
Classifier: License :: OSI Approved :: MIT License
Classifier: Natural Language :: English
Classifier: Programming Language :: Python :: 3
Classifier: Programming Language :: Python :: 3.6
Classifier: Programming Language :: Python :: 3.7
Classifier: Programming Language :: Python :: 3.8
Requires-Python: >=3.6
Requires-Dist: Click (>=7.0)
Requires-Dist: alembic (>=1.4.2)
